chawk/__init__.py
chawk/announcement.py
chawk/blackboard_client.py
chawk/course_client.py
chawk/discussion_client.py
chawk/endpoint_client.py
chawk/exceptions.py
chawk/formatting.py
chawk/grade_client.py
chawk/logger_client.py
chawk/py.typed
chawk/user_client.py
chawk-0.1.8.1.dist-info/METADATA
chawk-0.1.8.1.dist-info/WHEEL
chawk-0.1.8.1.dist-info/licenses/LICENSE
chawk-0.1.8.1.dist-info/RECORD
