Metadata-Version: 2.4
Name: chawk
Version: 0.1.8.1
Summary: An API wrapper library for the Blackboard LMS.
Project-URL: Homepage, https://codeberg.org/sugarvoid/chawk
Project-URL: Issues, https://codeberg.org/sugarvoid/chawk/issues
Author-email: sugarvoid <author@example.com>
License-Expression: MIT
License-File: LICENSE
Keywords: api,blackboard,lms,wrapper
Classifier: Intended Audience :: Developers
Classifier: License :: OSI Approved :: MIT License
Classifier: Operating System :: OS Independent
Classifier: Programming Language :: Python :: 3
Classifier: Programming Language :: Python :: 3.11
Classifier: Topic :: Software Development :: Libraries
Requires-Python: >=3.11
Requires-Dist: certifi==2024.12.14
Requires-Dist: charset-normalizer==3.4.0
Requires-Dist: idna==3.10
Requires-Dist: oauthlib==3.2.2
Requires-Dist: python-dotenv==1.0.1
Requires-Dist: requests-oauthlib==2.0.0
Requires-Dist: requests<3.0,>=2.32
Requires-Dist: urllib3==2.3.0
